ahttpx/__init__.py
ahttpx/__version__.py
ahttpx/_client.py
ahttpx/_content.py
ahttpx/_headers.py
ahttpx/_network.py
ahttpx/_parsers.py
ahttpx/_pool.py
ahttpx/_quickstart.py
ahttpx/_request.py
ahttpx/_response.py
ahttpx/_server.py
ahttpx/_streams.py
ahttpx/_urlencode.py
ahttpx/_urlparse.py
ahttpx/_urls.py
ahttpx-1.0.dev3.dist-info/METADATA
ahttpx-1.0.dev3.dist-info/WHEEL
ahttpx-1.0.dev3.dist-info/RECORD
